chordparser/__init__.py
chordparser/parser.py
chordparser/sample_sheet.cho
chordparser/analysers/__init__.py
chordparser/analysers/chords_analyser.py
chordparser/editors/__init__.py
chordparser/editors/chord_roman_converter.py
chordparser/editors/chords_editor.py
chordparser/editors/keys_editor.py
chordparser/editors/notes_editor.py
chordparser/editors/quality_editor.py
chordparser/editors/scales_editor.py
chordparser/music/__init__.py
chordparser/music/chords.py
chordparser/music/keys.py
chordparser/music/notes.py
chordparser/music/quality.py
chordparser/music/roman.py
chordparser/music/scales.py
chordparser-0.4.2.dist-info/AUTHORS.rst
chordparser-0.4.2.dist-info/LICENSE
chordparser-0.4.2.dist-info/METADATA
chordparser-0.4.2.dist-info/WHEEL
chordparser-0.4.2.dist-info/top_level.txt
chordparser-0.4.2.dist-info/RECORD
