Metadata-Version: 2.1
Name: chordparser
Version: 0.4.2
Summary: Parse and analyse chords
Home-page: http://github.com/titus-ong/chordparser
Author: Titus Ong
Author-email: titusongyl@gmail.com
License: MIT
Keywords: chords music parse notation analysis sheet notes scales keys transpose
Classifier: Development Status :: 4 - Beta
Classifier: License :: OSI Approved :: MIT License
Classifier: Operating System :: OS Independent
Classifier: Natural Language :: English
Classifier: Programming Language :: Python :: 3.6
Classifier: Programming Language :: Python :: 3.7
Classifier: Programming Language :: Python :: 3.8
Classifier: Topic :: Text Processing
Classifier: Topic :: Software Development :: Libraries :: Python Modules
License-File: LICENSE
License-File: AUTHORS.rst
